paystakk/__init__.py
paystakk/api.py
paystakk/auth.py
paystakk/keys.py
paystakk/request.py
paystakk/tests.py
paystakk/utils.py
paystakk-0.0.4.dist-info/LICENSE
paystakk-0.0.4.dist-info/METADATA
paystakk-0.0.4.dist-info/WHEEL
paystakk-0.0.4.dist-info/top_level.txt
paystakk-0.0.4.dist-info/RECORD
