Metadata-Version: 2.1
Name: paystakk
Version: 0.0.4
Summary: Unofficial Paystacks API wrapper
Home-page: UNKNOWN
Author: tundebabzy
Author-email: tundebabzy@gmail.com
License: MIT
Platform: UNKNOWN
